LICENSE
MANIFEST.in
README.rst
setup.py
subways/__init__.py
subways/factory.py
subways/process.py
subways/utils.py
subways.egg-info/PKG-INFO
subways.egg-info/SOURCES.txt
subways.egg-info/dependency_links.txt
subways.egg-info/top_level.txt