Metadata-Version: 1.1
Name: subways
Version: 0.1.0.dev7
Summary: A Python module that’s provide some basic utilities.
Home-page: https://github.com/midoriiro/subways/
Author: midoriiro
Author-email: contact@smartsoftwa.re
License: MIT License
